multivisor/__init__.py
multivisor/multivisor.py
multivisor/rpc.py
multivisor/signals.py
multivisor/util.py
multivisor/client/__init__.py
multivisor/client/cli.py
multivisor/client/http.py
multivisor/client/repl.py
multivisor/client/util.py
multivisor/server/__init__.py
multivisor/server/rpc.py
multivisor/server/util.py
multivisor/server/web.py
multivisor/server/dist/index.html
multivisor/server/dist/static/css/app.2aff3580a128440bba89b94112292cb1.css
multivisor/server/dist/static/css/app.2aff3580a128440bba89b94112292cb1.css.map
multivisor/server/dist/static/js/app.52791f915c2f060b9cb1.js
multivisor/server/dist/static/js/app.52791f915c2f060b9cb1.js.map
multivisor/server/dist/static/js/manifest.2ae2e69a05c33dfc65f8.js
multivisor/server/dist/static/js/manifest.2ae2e69a05c33dfc65f8.js.map
multivisor/server/dist/static/js/vendor.1d02877727062a41e9fb.js
multivisor/server/dist/static/js/vendor.1d02877727062a41e9fb.js.map
multivisor/server/tests/__init__.py
multivisor/server/tests/conftest.py
multivisor/server/tests/test_web.py
multivisor/tests/__init__.py
multivisor/tests/test_multivisor.py
multivisor-6.0.2.dist-info/licenses/LICENSE
multivisor-6.0.2.dist-info/METADATA
multivisor-6.0.2.dist-info/WHEEL
multivisor-6.0.2.dist-info/entry_points.txt
multivisor-6.0.2.dist-info/top_level.txt
multivisor-6.0.2.dist-info/RECORD
