Metadata-Version: 2.4
Name: multivisor
Version: 6.0.2
Summary: A centralized supervisor UI (web & CLI)
Author: Tiago Coutinho
Author-email: coutinhotiago@gmail.com
License: GNU General Public License v3
Classifier: Development Status :: 4 - Beta
Classifier: Environment :: Console
Classifier: Environment :: Web Environment
Classifier: Framework :: Flask
Classifier: Intended Audience :: Developers
Classifier: Intended Audience :: Information Technology
Classifier: Intended Audience :: System Administrators
Classifier: License :: OSI Approved :: GNU General Public License v3 (GPLv3)
Classifier: Natural Language :: English
Classifier: Operating System :: POSIX
Classifier: Operating System :: Microsoft :: Windows
Classifier: Programming Language :: Python
Classifier: Programming Language :: Python :: 2
Classifier: Programming Language :: Python :: 2.7
Classifier: Programming Language :: Python :: 3
Classifier: Programming Language :: Python :: 3.5
Classifier: Programming Language :: Python :: 3.6
Classifier: Programming Language :: Python :: 3.7
Classifier: Programming Language :: Python :: 3.8
Classifier: Programming Language :: Python :: 3.9
Classifier: Topic :: System :: Boot
Classifier: Topic :: System :: Monitoring
Classifier: Topic :: System :: Systems Administration
License-File: LICENSE
Requires-Dist: six
Requires-Dist: gevent>=1.3
Provides-Extra: rpc
Requires-Dist: zerorpc; extra == "rpc"
Requires-Dist: supervisor; extra == "rpc"
Provides-Extra: web
Requires-Dist: flask; extra == "web"
Requires-Dist: werkzeug; extra == "web"
Requires-Dist: blinker; extra == "web"
Requires-Dist: zerorpc; extra == "web"
Requires-Dist: supervisor; extra == "web"
Provides-Extra: cli
Requires-Dist: maya; extra == "cli"
Requires-Dist: requests; extra == "cli"
Requires-Dist: prompt_toolkit>=2; extra == "cli"
Requires-Dist: blinker; extra == "cli"
Provides-Extra: all
Requires-Dist: maya; extra == "all"
Requires-Dist: requests; extra == "all"
Requires-Dist: supervisor; extra == "all"
Requires-Dist: flask; extra == "all"
Requires-Dist: zerorpc; extra == "all"
Requires-Dist: blinker; extra == "all"
Requires-Dist: prompt_toolkit>=2; extra == "all"
Requires-Dist: werkzeug; extra == "all"
Dynamic: author
Dynamic: author-email
Dynamic: classifier
Dynamic: description
Dynamic: description-content-type
Dynamic: license
Dynamic: license-file
Dynamic: provides-extra
Dynamic: requires-dist
Dynamic: summary
